Metadata-Version: 2.1
Name: import-for-gcp
Version: 0.1.2
Summary: Use to import classes from .py files saved on google cloud storage
Home-page: UNKNOWN
Author: Caleb Hopkins
Author-email: caleb.hopkins@method.com
License: UNKNOWN
Platform: UNKNOWN
Classifier: Programming Language :: Python :: 3
Classifier: License :: OSI Approved :: MIT License
Classifier: Operating System :: OS Independent
Requires-Python: >=3.9
